_pypolychord.cpython-37m-x86_64-linux-gnu.so
pypolychord-1.15.1.dist-info/WHEEL
pypolychord-1.15.1.dist-info/top_level.txt
pypolychord-1.15.1.dist-info/METADATA
pypolychord-1.15.1.dist-info/RECORD
pypolychord/priors.py
pypolychord/output.py
pypolychord/settings.py
pypolychord/__init__.py
pypolychord/libs_pypolychord/libopen-rte-be60cdb2.so.20.10.4
pypolychord/libs_pypolychord/libmpi_mpifh-3bac19fe.so.20.12.1
pypolychord/libs_pypolychord/libopen-pal-2f5201c7.so.20.10.4
pypolychord/libs_pypolychord/libchord-26d2ce45.so
pypolychord/libs_pypolychord/libmpi_usempi-91f89651.so.20.12.0
pypolychord/libs_pypolychord/libmpi-53321f99.so.20.10.3
pypolychord/libs_pypolychord/libgfortran-ed201abd.so.3.0.0
