Metadata-Version: 2.1
Name: pypolychord
Version: 1.15.1
Summary: Python interface to PolyChord
Home-page: https://ccpforge.cse.rl.ac.uk/gf/project/polychord/
Author: Will Handley
Author-email: wh260@cam.ac.uk
License: PolyChord
Platform: UNKNOWN
Provides-Extra: plotting
Requires-Dist: numpy
Requires-Dist: scipy
Provides-Extra: plotting
Requires-Dist: getdist; extra == 'plotting'
